machine_learning_utility/__init__.py
machine_learning_utility/encode_categorical.py
machine_learning_utility-1.0.dist-info/LICENSE
machine_learning_utility-1.0.dist-info/METADATA
machine_learning_utility-1.0.dist-info/WHEEL
machine_learning_utility-1.0.dist-info/top_level.txt
machine_learning_utility-1.0.dist-info/RECORD
